README.md
setup.cfg
setup.py
dynalist/__init__.py
dynalist/__version__.py
dynalist/dynalist.py
dynalist.egg-info/PKG-INFO
dynalist.egg-info/SOURCES.txt
dynalist.egg-info/dependency_links.txt
dynalist.egg-info/requires.txt
dynalist.egg-info/top_level.txt