Metadata-Version: 2.1
Name: dynalist
Version: 0.2.6
Summary: Unofficial Dynalist API Written in Python
Home-page: https://github.com/georgefeng/dynalist
Author: feng
Author-email: edu_feng@163.com
License: The MIT License (MIT)
Keywords: dynalist,api
Platform: UNKNOWN
Classifier: Operating System :: OS Independent
Classifier: Intended Audience :: Developers
Classifier: License :: OSI Approved :: MIT License
Classifier: Programming Language :: Python
Classifier: Programming Language :: Python :: Implementation
Classifier: Programming Language :: Python :: 3
Classifier: Programming Language :: Python :: 3.4
Classifier: Programming Language :: Python :: 3.5
Classifier: Programming Language :: Python :: 3.6
